setup.py
dist_proba/Binomialdistribution.py
dist_proba/Gaussiandistribution.py
dist_proba/Generaldistribution.py
dist_proba/__init__.py
dist_proba.egg-info/PKG-INFO
dist_proba.egg-info/SOURCES.txt
dist_proba.egg-info/dependency_links.txt
dist_proba.egg-info/not-zip-safe
dist_proba.egg-info/top_level.txt