Metadata-Version: 1.0
Name: dist-proba
Version: 0.1
Summary: Gaussian and Binomial distributions
Home-page: UNKNOWN
Author: Christophe Berset
Author-email: bersetchristophe@gmail.com
License: UNKNOWN
Platform: UNKNOWN
